xcommand/__init__.py
xcommand/pdf.py
xcommand/report.py
xcommand-0.2.dist-info/LICENSE
xcommand-0.2.dist-info/METADATA
xcommand-0.2.dist-info/WHEEL
xcommand-0.2.dist-info/entry_points.txt
xcommand-0.2.dist-info/top_level.txt
xcommand-0.2.dist-info/RECORD
