Metadata-Version: 2.1
Name: xcommand
Version: 0.2
Summary: 个人常用命令行工具合集
Home-page: UNKNOWN
Author: 二炜
Author-email: 1174543101@qq.com
License: UNKNOWN
Platform: UNKNOWN
Classifier: Programming Language :: Python :: 3
Classifier: License :: OSI Approved :: MIT License
Classifier: Operating System :: Microsoft :: Windows
License-File: LICENSE
Requires-Dist: click
Requires-Dist: PyMuPDF
Requires-Dist: img2pdf
Requires-Dist: pywin32
